emailsmtp_client.py
emailsmtp_client-0.0.2.dist-info/METADATA
emailsmtp_client-0.0.2.dist-info/WHEEL
emailsmtp_client-0.0.2.dist-info/top_level.txt
emailsmtp_client-0.0.2.dist-info/RECORD
