Metadata-Version: 2.1
Name: emailsmtp-client
Version: 0.0.2
Summary: yess
Home-page: UNKNOWN
Author: champu bai dan
Author-email: temporarywebhosting@gmail.com
License: UNKNOWN
Keywords: python,hacking,cybersecurity,hacking tools,security testing,hacker
Platform: UNKNOWN
Classifier: Development Status :: 1 - Planning
Classifier: Intended Audience :: Developers
Classifier: Programming Language :: Python :: 3
Classifier: Operating System :: Unix
Classifier: Operating System :: MacOS :: MacOS X
Classifier: Operating System :: Microsoft :: Windows
Requires-Dist: mysql.connector
